local_qwen3b_meta/__init__.py
local_qwen3b_meta-0.0.1.dist-info/METADATA
local_qwen3b_meta-0.0.1.dist-info/WHEEL
local_qwen3b_meta-0.0.1.dist-info/top_level.txt
local_qwen3b_meta-0.0.1.dist-info/RECORD
