Metadata-Version: 2.4
Name: local_qwen3b_meta
Version: 0.0.1
Summary: Meta package for qwen2.5-3b-instruct-q5_k_m.gguf
Requires-Python: >=3.9
Requires-Dist: local_qwen3b_part000==0.0.1
Requires-Dist: local_qwen3b_part001==0.0.1
Requires-Dist: local_qwen3b_part002==0.0.1
Requires-Dist: local_qwen3b_part003==0.0.1
Requires-Dist: local_qwen3b_part004==0.0.1
Requires-Dist: local_qwen3b_part005==0.0.1
Requires-Dist: local_qwen3b_part006==0.0.1
Requires-Dist: local_qwen3b_part007==0.0.1
Requires-Dist: local_qwen3b_part008==0.0.1
Requires-Dist: local_qwen3b_part009==0.0.1
Requires-Dist: local_qwen3b_part010==0.0.1
Requires-Dist: local_qwen3b_part011==0.0.1
Requires-Dist: local_qwen3b_part012==0.0.1
Requires-Dist: local_qwen3b_part013==0.0.1
Requires-Dist: local_qwen3b_part014==0.0.1
Requires-Dist: local_qwen3b_part015==0.0.1
Requires-Dist: local_qwen3b_part016==0.0.1
Requires-Dist: local_qwen3b_part017==0.0.1
Requires-Dist: local_qwen3b_part018==0.0.1
Requires-Dist: local_qwen3b_part019==0.0.1
Requires-Dist: local_qwen3b_part020==0.0.1
Requires-Dist: local_qwen3b_part021==0.0.1
Requires-Dist: local_qwen3b_part022==0.0.1
Requires-Dist: local_qwen3b_part023==0.0.1
Requires-Dist: local_qwen3b_part024==0.0.1
Requires-Dist: local_qwen3b_part025==0.0.1
Requires-Dist: local_qwen3b_part026==0.0.1
Requires-Dist: local_qwen3b_part027==0.0.1
Requires-Dist: local_qwen3b_part028==0.0.1
Requires-Dist: local_qwen3b_part029==0.0.1
Requires-Dist: local_qwen3b_part030==0.0.1
Requires-Dist: local_qwen3b_part031==0.0.1
Requires-Dist: local_qwen3b_part032==0.0.1
Requires-Dist: local_qwen3b_part033==0.0.1
Requires-Dist: local_qwen3b_part034==0.0.1
Requires-Dist: local_qwen3b_part035==0.0.1
Requires-Dist: local_qwen3b_part036==0.0.1
